[
  {
    "name" : "lightline.vim",
    "rev" : "b:master",
    "docDir" : "doc",
    "oid" : "c172131e0369672bc1b9454a2aec6d532d350dcc",
    "type" : "start",
    "origin" : "https:\/\/github.com\/itchyny\/lightline.vim"
  },
  {
    "name" : "ctrlp.vim",
    "docDir" : "doc",
    "origin" : "https:\/\/github.com\/ctrlpvim\/ctrlp.vim",
    "rev" : "b:master",
    "oid" : "d93d97813dc839ef0782302a0debd7c4877f09f3",
    "type" : "start"
  },
  {
    "origin" : "https:\/\/github.com\/suliveevil\/helptab.vim",
    "oid" : "57fca55f8e370bc05df41690332a5bd419a22349",
    "rev" : "b:master",
    "name" : "helptab.vim",
    "type" : "start",
    "docDir" : "doc"
  },
  {
    "name" : "indentLine",
    "type" : "start",
    "docDir" : "doc",
    "origin" : "https:\/\/github.com\/Yggdroot\/indentLine",
    "rev" : "b:master",
    "oid" : "43dbd7092801637972b1d9fcecaaeee11f8e00cf"
  },
  {
    "type" : "start",
    "origin" : "https:\/\/github.com\/preservim\/nerdcommenter",
    "rev" : "b:master",
    "oid" : "fade3d4b26f5a0d58f256a06ba7b0a04d9fb4f3b",
    "name" : "nerdcommenter",
    "docDir" : "doc"
  },
  {
    "docDir" : "doc",
    "oid" : "d48ab70721d4f688ed34bd5939e2d6f4c89548c5",
    "origin" : "https:\/\/github.com\/preservim\/nerdtree",
    "name" : "nerdtree",
    "type" : "start",
    "rev" : "b:master"
  },
  {
    "type" : "start",
    "origin" : "https:\/\/github.com\/luochen1990\/rainbow",
    "oid" : "4d15633cdaf61602e1d9fd216a77fc02e0881b2d",
    "docDir" : "doc",
    "rev" : "b:master",
    "name" : "rainbow"
  },
  {
    "oid" : "fcabc99ca606ea0ddd4379e7710bb4bf90d2d0f5",
    "name" : "tagbar",
    "docDir" : "doc",
    "origin" : "https:\/\/github.com\/majutsushi\/tagbar",
    "rev" : "b:master",
    "type" : "start"
  },
  {
    "type" : "start",
    "rev" : "b:master",
    "oid" : "e83c82099d9bd43dc7895e3cb5b114ee5a2a07c6",
    "name" : "ultisnips",
    "docDir" : "doc",
    "origin" : "https:\/\/github.com\/SirVer\/ultisnips"
  },
  {
    "type" : "start",
    "oid" : "76e95c6f8c863f5079cd103b18990684bb02d525",
    "origin" : "https:\/\/github.com\/chrisbra\/unicode.vim",
    "name" : "unicode.vim",
    "docDir" : "doc",
    "rev" : "b:master"
  },
  {
    "docDir" : "doc",
    "rev" : "b:master",
    "type" : "start",
    "oid" : "12dd6316974f71ce333e360c0260b4e1f81169c3",
    "name" : "vim-easy-align",
    "origin" : "https:\/\/github.com\/junegunn\/vim-easy-align"
  },
  {
    "rev" : "b:master",
    "name" : "vim-easymotion",
    "type" : "start",
    "oid" : "dd7b4b526775bc8553e16bc402020573b04a948c",
    "docDir" : "doc",
    "origin" : "https:\/\/github.com\/easymotion\/vim-easymotion"
  },
  {
    "origin" : "https:\/\/github.com\/liuchengxu\/vim-which-key",
    "docDir" : "doc",
    "oid" : "dffbb044f7974bf4615960689a3ff64e63daeab3",
    "name" : "vim-which-key",
    "rev" : "b:master",
    "type" : "start"
  },
  {
    "name" : "vim-vinegar",
    "docDir" : "doc",
    "rev" : "b:master",
    "type" : "start",
    "oid" : "fcce70f1403ba4101668a4c960c577bddbd00f06",
    "origin" : "https:\/\/github.com\/tpope\/vim-vinegar"
  },
  {
    "name" : "vim-unimpaired",
    "rev" : "b:master",
    "docDir" : "doc",
    "type" : "start",
    "oid" : "4afbe5ebf32ad85341b4c02b0e1d8ca96a64c561",
    "origin" : "https:\/\/github.com\/tpope\/vim-unimpaired"
  },
  {
    "name" : "vim-surround",
    "rev" : "b:master",
    "oid" : "f51a26d3710629d031806305b6c8727189cd1935",
    "type" : "start",
    "docDir" : "doc",
    "origin" : "https:\/\/github.com\/tpope\/vim-surround"
  },
  {
    "type" : "start",
    "rev" : "b:master",
    "origin" : "https:\/\/github.com\/tpope\/vim-repeat",
    "name" : "vim-repeat",
    "oid" : "c947ad2b6a16983724a0153bdf7f66d7a80a32ca"
  },
  {
    "rev" : "b:master",
    "oid" : "8c64cae9710f6f44dde98f0a590219b95b2da9ab",
    "name" : "vim-redir-output",
    "origin" : "https:\/\/github.com\/suliveevil\/vim-redir-output",
    "type" : "start"
  },
  {
    "type" : "start",
    "name" : "hiPairs",
    "origin" : "https:\/\/github.com\/suliveevil\/hiPairs",
    "rev" : "b:master",
    "oid" : "f25963661acfb8b886952221c5f2db03601277e0"
  },
  {
    "rev" : "b:master",
    "name" : "vim-illuminate",
    "oid" : "0778289e391c419f7a3af9de8229f798ee292013",
    "docDir" : "doc",
    "type" : "start",
    "origin" : "https:\/\/github.com\/RRethy\/vim-illuminate"
  },
  {
    "origin" : "https:\/\/github.com\/plasticboy\/vim-markdown",
    "name" : "vim-markdown",
    "type" : "start",
    "rev" : "b:master",
    "docDir" : "doc",
    "oid" : "da5a7ac96f517e0fd6f886bc3fbe27156ca1f946"
  },
  {
    "oid" : "046fc0664b953ab17153da379df0b9fd34b85ec1",
    "origin" : "https:\/\/github.com\/suliveevil\/vim-mundo",
    "docDir" : "doc",
    "rev" : "b:master",
    "type" : "start",
    "name" : "vim-mundo"
  },
  {
    "oid" : "baaaad0d377bce2e78823ce10cebdd50e4bbf41a",
    "name" : "vim-pythonsense",
    "docDir" : "doc",
    "type" : "start",
    "rev" : "b:master",
    "origin" : "https:\/\/github.com\/suliveevil\/vim-pythonsense"
  },
  {
    "origin" : "https:\/\/github.com\/kana\/vim-textobj-user",
    "rev" : "b:master",
    "docDir" : "doc",
    "oid" : "41a675ddbeefd6a93664a4dc52f302fe3086a933",
    "name" : "vim-textobj-user",
    "type" : "start"
  },
  {
    "origin" : "https:\/\/github.com\/mg979\/vim-visual-multi",
    "docDir" : "doc",
    "oid" : "f972b5357af0e5c9b840f8e82eceb313891ef8b2",
    "rev" : "b:master",
    "name" : "vim-visual-multi",
    "type" : "start"
  },
  {
    "rev" : "b:master",
    "name" : "goyo.vim",
    "origin" : "https:\/\/github.com\/junegunn\/goyo.vim",
    "type" : "start",
    "docDir" : "doc",
    "oid" : "3e129198bba7d6b50406902002ad7d213a6cccaa"
  },
  {
    "origin" : "https:\/\/github.com\/junegunn\/limelight.vim",
    "rev" : "b:master",
    "name" : "limelight.vim",
    "type" : "start",
    "oid" : "26e913a2e061195245bc62d24009ab67143a3c32"
  },
  {
    "name" : "vim-easymotion-chs",
    "oid" : "05d41216942255f6ec0ad1d04339e2fe3b90a460",
    "rev" : "b:master",
    "origin" : "https:\/\/github.com\/ZSaberLv0\/vim-easymotion-chs",
    "type" : "start"
  },
  {
    "oid" : "0f83788cb67e0743a3a9c8d3a3a6e52a01bdc6c2",
    "origin" : "https:\/\/github.com\/Shougo\/neocomplete",
    "docDir" : "doc",
    "name" : "neocomplete",
    "type" : "start",
    "rev" : "b:master"
  },
  {
    "name" : "vim-gutentags",
    "oid" : "8e69652c7a7e7aabd96cff21b6ee6b6a295c901c",
    "type" : "start",
    "docDir" : "doc",
    "rev" : "b:master",
    "origin" : "https:\/\/github.com\/ludovicchabant\/vim-gutentags"
  },
  {
    "docDir" : "doc",
    "oid" : "27a5c3abd211c2784513dab4db082fa414ad0967",
    "type" : "start",
    "rev" : "b:master",
    "origin" : "https:\/\/github.com\/tpope\/vim-fugitive",
    "name" : "vim-fugitive"
  },
  {
    "oid" : "17b349d49156887d9203e3fac6fa072746f505c0",
    "docDir" : "doc",
    "name" : "vim-yoink",
    "rev" : "b:master",
    "origin" : "https:\/\/github.com\/svermeulen\/vim-yoink",
    "type" : "start"
  },
  {
    "rev" : "b:master",
    "name" : "vimcdoc",
    "oid" : "2c660f187009cedd9e35ca8939a10613c7f0bd20",
    "origin" : "https:\/\/github.com\/yianwillis\/vimcdoc",
    "docDir" : "doc",
    "type" : "start"
  },
  {
    "oid" : "e49f9e7e3fc041dab0e9a1de4b564b3ddd8f77aa",
    "origin" : "https:\/\/github.com\/vim-pandoc\/vim-pandoc",
    "type" : "start",
    "name" : "vim-pandoc",
    "rev" : "b:master",
    "docDir" : "doc"
  },
  {
    "name" : "vim-pandoc-syntax",
    "origin" : "https:\/\/github.com\/vim-pandoc\/vim-pandoc-syntax",
    "rev" : "b:master",
    "docDir" : "doc",
    "type" : "start",
    "oid" : "0d1129e5cf1b0e3a90e923c3b5f40133bf153f7c"
  },
  {
    "type" : "start",
    "docDir" : "doc",
    "rev" : "b:master",
    "oid" : "33f0fabef78a82d409f2431a1698d131b4f041f0",
    "origin" : "https:\/\/github.com\/lambdalisue\/fern.vim",
    "name" : "fern.vim"
  },
  {
    "rev" : "b:master",
    "origin" : "https:\/\/github.com\/tyru\/open-browser.vim",
    "oid" : "d6f1784685abdd86500fdb5fa2fbaf2aab833f18",
    "type" : "start",
    "docDir" : "doc",
    "name" : "open-browser.vim"
  },
  {
    "origin" : "https:\/\/github.com\/chrisbra\/Colorizer",
    "rev" : "b:master",
    "name" : "Colorizer",
    "docDir" : "doc",
    "oid" : "879e6c69c0c02c4ef0f08b3955c60de16efd8fb8",
    "type" : "start"
  },
  {
    "rev" : "b:master",
    "oid" : "b22f49fe10969e1b821d8dba25fff86f6b4df966",
    "origin" : "https:\/\/github.com\/itchyny\/vim-grep",
    "name" : "vim-grep",
    "type" : "start"
  },
  {
    "type" : "start",
    "origin" : "https:\/\/github.com\/suliveevil\/vim-plist",
    "name" : "vim-plist",
    "oid" : "12dce205a219321423de9fd3175e7bcc1c7d135d",
    "rev" : "b:master"
  },
  {
    "name" : "python-mode",
    "origin" : "https:\/\/github.com\/python-mode\/python-mode",
    "docDir" : "doc",
    "oid" : "51c66faf14b824ee5d6ddfc5a54530d9f92fe764",
    "rev" : "b:develop",
    "type" : "start"
  },
  {
    "origin" : "https:\/\/github.com\/lervag\/vimtex",
    "docDir" : "doc",
    "rev" : "b:master",
    "name" : "vimtex",
    "type" : "start",
    "oid" : "49bc335fffa40a7b7b84b6110b57ebcbaaf019ea"
  },
  {
    "origin" : "https:\/\/github.com\/sbdchd\/neoformat",
    "name" : "neoformat",
    "docDir" : "doc",
    "type" : "start",
    "rev" : "b:master",
    "oid" : "55c659d3429f09ebb818615056a86a67901f022c"
  },
  {
    "origin" : "https:\/\/github.com\/jpalardy\/vim-slime",
    "oid" : "a81139239d6447b1c021e4873e6a14b47f32b65a",
    "type" : "start",
    "docDir" : "doc",
    "rev" : "b:master",
    "name" : "vim-slime"
  },
  {
    "rev" : "b:master",
    "oid" : "4172542f92b56cb639b8d2548516f6e4e0eb61e0",
    "type" : "start",
    "name" : "vim-repl",
    "origin" : "https:\/\/github.com\/sillybun\/vim-repl"
  },
  {
    "docDir" : "doc",
    "name" : "vim-orgmode",
    "type" : "start",
    "oid" : "ecdc5b279d7b4e0ae4ebfb9e0f139e3ca6698033",
    "origin" : "https:\/\/github.com\/jceb\/vim-orgmode",
    "rev" : "b:master"
  },
  {
    "rev" : "b:master",
    "type" : "start",
    "name" : "vim-speeddating",
    "docDir" : "doc",
    "oid" : "fe98cfaa7ea9c4b838d42a6830437c919eb55b4e",
    "origin" : "https:\/\/github.com\/tpope\/vim-speeddating"
  },
  {
    "name" : "findr.vim",
    "docDir" : "doc",
    "type" : "start",
    "oid" : "92126073e8ac1df8d864c062853df68a243f4f2f",
    "origin" : "https:\/\/github.com\/conweller\/findr.vim",
    "rev" : "b:master"
  },
  {
    "name" : "vim-colors-solarized",
    "origin" : "https:\/\/github.com\/altercation\/vim-colors-solarized.git",
    "rev" : "b:master",
    "type" : "opt",
    "oid" : "528a59f26d12278698bb946f8fb82a63711eec21",
    "docDir" : "doc"
  },
  {
    "type" : "start",
    "origin" : "https:\/\/github.com\/suliveevil\/ivim-snippets",
    "oid" : "7a2e8de935deeae65c449e950a5ddbc7e7d79369",
    "name" : "ivim-snippets",
    "rev" : "b:master"
  },
  {
    "type" : "start",
    "origin" : "https:\/\/github.com\/Yggdroot\/LeaderF",
    "docDir" : "doc",
    "rev" : "b:master",
    "oid" : "570e0a428bc0ac43ab7a59784b9b2a33356840dc",
    "name" : "LeaderF"
  },
  {
    "name" : "searchvim",
    "type" : "start",
    "oid" : "a72f27c1d88fad67f87c6394f15e834d1721fed2",
    "origin" : "https:\/\/github.com\/nonameentername\/searchvim",
    "rev" : "b:master"
  }
]